README.txt
setup.cfg
setup.py
GNotifier.egg-info/PKG-INFO
GNotifier.egg-info/SOURCES.txt
GNotifier.egg-info/dependency_links.txt
GNotifier.egg-info/entry_points.txt
GNotifier.egg-info/not-zip-safe
GNotifier.egg-info/requires.txt
GNotifier.egg-info/top_level.txt
notifier/__init__.py
notifier/server.py
notifier/xmpp/__init__.py
notifier/xmpp/auth.py
notifier/xmpp/browser.py
notifier/xmpp/client.py
notifier/xmpp/commands.py
notifier/xmpp/debug.py
notifier/xmpp/dispatcher.py
notifier/xmpp/features.py
notifier/xmpp/filetransfer.py
notifier/xmpp/jep0106.py
notifier/xmpp/protocol.py
notifier/xmpp/roster.py
notifier/xmpp/session.py
notifier/xmpp/simplexml.py
notifier/xmpp/transports.py