Metadata-Version: 1.0
Name: GNotifier
Version: 0.5
Summary: web service to send notification via gmail/gtalk
Home-page: http://www.gawel.org/docs/GNotifier/index.html
Author: Gael Pasgrimaud
Author-email: gael@gawel.org
License: MIT
Keywords: google gtalk gmail notification
Platform: UNKNOWN
